odoo8_addon_res_partner_affiliate-8.0.1.0.0.99.dev10-py2.7-nspkg.pth
odoo8_addon_res_partner_affiliate-8.0.1.0.0.99.dev10.dist-info/DESCRIPTION.rst
odoo8_addon_res_partner_affiliate-8.0.1.0.0.99.dev10.dist-info/METADATA
odoo8_addon_res_partner_affiliate-8.0.1.0.0.99.dev10.dist-info/RECORD
odoo8_addon_res_partner_affiliate-8.0.1.0.0.99.dev10.dist-info/WHEEL
odoo8_addon_res_partner_affiliate-8.0.1.0.0.99.dev10.dist-info/metadata.json
odoo8_addon_res_partner_affiliate-8.0.1.0.0.99.dev10.dist-info/namespace_packages.txt
odoo8_addon_res_partner_affiliate-8.0.1.0.0.99.dev10.dist-info/top_level.txt
odoo_addons/res_partner_affiliate/__init__.py
odoo_addons/res_partner_affiliate/__openerp__.py
odoo_addons/res_partner_affiliate/res_partner.py
odoo_addons/res_partner_affiliate/res_partner_view.xml
odoo_addons/res_partner_affiliate/i18n/de.po
odoo_addons/res_partner_affiliate/i18n/es.po
odoo_addons/res_partner_affiliate/i18n/eu.po
odoo_addons/res_partner_affiliate/i18n/fi.po
odoo_addons/res_partner_affiliate/i18n/fr.po
odoo_addons/res_partner_affiliate/i18n/it.po
odoo_addons/res_partner_affiliate/i18n/nl.po
odoo_addons/res_partner_affiliate/i18n/pt_BR.po
odoo_addons/res_partner_affiliate/i18n/res_partner_affiliate.pot
odoo_addons/res_partner_affiliate/i18n/sl.po
odoo_addons/res_partner_affiliate/static/description/icon.png
